yqn_project_pro/README.md
yqn_project_pro/__init__.py
yqn_project_pro/log/__init__.py
yqn_project_pro/log/helper.py
yqn_project_pro/log/logger.py
yqn_project_pro/rpc/__init__.py
yqn_project_pro/rpc/es.py
yqn_project_pro/rpc/mysql_.py
yqn_project_pro/rpc/odps_.py
yqn_project_pro/rpc/apollo/__init__.py
yqn_project_pro/rpc/apollo/apollo_client.py
yqn_project_pro/rpc/apollo/apollo_config.py
yqn_project_pro/rpc/eureka/__init__.py
yqn_project_pro/rpc/eureka/eureka_client.py
yqn_project_pro/rpc/eureka/eureka_config.py
yqn_project_pro/rpc/eureka/eureka_request.py
yqn_project_pro/utils/__init__.py
yqn_project_pro/utils/api.py
yqn_project_pro/utils/app.py
yqn_project_pro/utils/check_token.py
yqn_project_pro/utils/decorators.py
yqn_project_pro/utils/download_file.py
yqn_project_pro/utils/lazy.py
yqn_project_pro/utils/oss_func.py
yqn_project_pro/utils/portal.py
yqn_project_pro/utils/restx.py
yqn_project_pro/utils/sha512_aes_256.py
yqn_project_pro/utils/strings.py
yqn_project_pro/utils/core/__init__.py
yqn_project_pro/utils/core/as_flask.py
yqn_project_pro/utils/core/config.py
yqn_project_pro/utils/core/exceptions.py
yqn_project_pro/utils/core/logger.py
yqn_project_pro/utils/core/parser.py
yqn_project_pro/utils/core/request.py
yqn_project_pro/utils/core/response.py
yqn_project_pro/yqn_config/__init__.py
yqn_project_pro/yqn_config/base_config.py
yqn_project_pro/yqn_config/conf_parser.py
yqn_project_pro/yqn_ops/__init__.py
yqn_project_pro/yqn_ops/download_resource.py
yqn_project_pro-0.0.4.dist-info/LICENSE
yqn_project_pro-0.0.4.dist-info/METADATA
yqn_project_pro-0.0.4.dist-info/WHEEL
yqn_project_pro-0.0.4.dist-info/entry_points.txt
yqn_project_pro-0.0.4.dist-info/top_level.txt
yqn_project_pro-0.0.4.dist-info/RECORD
